{
    "Name"          : "dejavu-fonts-ttf",
    "Version"       : "2.35",
    "Url"           : "http://downloads.sourceforge.net/project/dejavu/dejavu/2.35/dejavu-fonts-ttf-2.35.tar.bz2",
    "Group"         : "x11",
    "StageDir"      : "",
    "Inherit"       : "",
    "Cid"           : "",
    "BuildInStage"  : true,
    "IsRebuilt"     : false,
    "BuildTime"     : 0,
    "Date"          : "2019-01-29T20:33:27.757049327-08:00",
    "Size"          : 0,
    "SubPackages"   : null,
    "AutoDepends"   : null,
    "ManualDepends" : null,
    "BuildDepends"  : null,
    "Flags"         : null,
    "Patch"         : null,
    "Build"         : null,
    "Package"       : [
                    "install -dm755 $PKGDIR/$PREFIX/etc/fonts/conf.avail",
                    "install -dm755 $PKGDIR/$PREFIX/share/fonts/TTF",
                    "install -m644 ttf/*.ttf $PKGDIR/$PREFIX/share/fonts/TTF/",
                    "install -m644 fontconfig/*.conf $PKGDIR/$PREFIX/etc/fonts/conf.avail/"
    ],
    "PostInstall" : null,
    "Remove"      : null,
    "Files"       : null
}
