{
    "Name"          : "glproto",
    "Version"       : "1.4.17",
    "Url"           : "http://xorg.freedesktop.org/releases/individual/proto/glproto-1.4.17.tar.bz2",
    "Group"         : "x11",
    "StageDir"      : "",
    "Inherit"       : "gnu",
    "Oid"           : "86FDDDDB58545B0D46CA7EF6B78CE99570F526CB22CBC0DCAD859B6EE415E532",
    "BuildInStage"  : false,
    "IsRebuilt"     : false,
    "BuildTime"     : 0,
    "Date"          : "2017-10-16T12:48:10.84766489-07:00",
    "Size"          : 105708,
    "SubPackages"   : null,
    "AutoDepends"   : [],
    "ManualDepends" : null,
    "BuildDepends"  : null,
    "Flags"         : null,
    "Patch"         : null,
    "Build"         : null,
    "Package"       : null,
    "PostInstall"   : null,
    "Remove"        : null,
    "Files"         : [
                    "tmp/via/include/GL/glxint.h",
                    "tmp/via/include/GL/glxmd.h",
                    "tmp/via/include/GL/glxproto.h",
                    "tmp/via/include/GL/glxtokens.h",
                    "tmp/via/include/GL/internal/glcore.h",
                    "tmp/via/lib/pkgconfig/glproto.pc"
    ]
}
