{
    "Name"          : "inputproto",
    "Version"       : "2.3.1",
    "Url"           : "http://xorg.freedesktop.org//releases/individual/proto/inputproto-2.3.1.tar.bz2",
    "Group"         : "x11",
    "StageDir"      : "",
    "Inherit"       : "gnu",
    "Oid"           : "",
    "BuildInStage"  : false,
    "BuildTime"     : 0,
    "Date"          : "2016-03-10T02:06:25.294747266-08:00",
    "Size"          : 100705,
    "SubPackages"   : null,
    "AutoDepends"   : null,
    "ManualDepends" : null,
    "BuildDepends"  : null,
    "Flags"         : null,
    "Patch"         : null,
    "Build"         : null,
    "Package"       : null,
    "PostInstall"   : null,
    "Remove"        : null,
    "Files"         : [
                    "home/mrosset/.local/include/X11/extensions/XI.h",
                    "home/mrosset/.local/include/X11/extensions/XI2.h",
                    "home/mrosset/.local/include/X11/extensions/XI2proto.h",
                    "home/mrosset/.local/include/X11/extensions/XIproto.h",
                    "home/mrosset/.local/lib/pkgconfig/inputproto.pc"
    ]
}
