{
    "Name"         : "libXdamage",
    "Version"      : "1.1.4",
    "Url"          : "http://xorg.freedesktop.org//releases/individual/lib/libXdamage-1.1.4.tar.bz2",
    "Group"        : "x11",
    "StageDir"     : "",
    "Inherit"      : "gnu",
    "Cid"          : "QmbGZ4W7hpriz8dbP6KvAHBmDyEPg28JpF2t2T6mESkj21",
    "BuildInStage" : false,
    "IsRebuilt"    : false,
    "BuildTime"    : 0,
    "Date"         : "2019-01-02T23:14:05.341119794-08:00",
    "Size"         : 20985,
    "SubPackages"  : null,
    "AutoDepends"  : [
                   "glibc",
                   "libX11",
                   "libXfixes",
                   "libxau",
                   "libxcb"
    ],
    "ManualDepends" : [
                    "damageproto"
    ],
    "BuildDepends" : null,
    "Flags"        : null,
    "Patch"        : null,
    "Build"        : null,
    "Package"      : null,
    "PostInstall"  : null,
    "Remove"       : null,
    "Files"        : [
                   "home/mrosset/via/include/X11/extensions/Xdamage.h",
                   "home/mrosset/via/lib/libXdamage.a",
                   "home/mrosset/via/lib/libXdamage.la",
                   "home/mrosset/via/lib/libXdamage.so",
                   "home/mrosset/via/lib/libXdamage.so.1",
                   "home/mrosset/via/lib/libXdamage.so.1.1.0",
                   "home/mrosset/via/lib/pkgconfig/xdamage.pc"
    ]
}
