{
    "Name"          : "libjpeg-turbo",
    "Version"       : "1.4.2",
    "Url"           : "http://downloads.sourceforge.net/project/libjpeg-turbo/1.4.2/libjpeg-turbo-1.4.2.tar.gz",
    "Group"         : "extra",
    "StageDir"      : "",
    "Inherit"       : "gnu",
    "Oid"           : "",
    "BuildInStage"  : false,
    "BuildTime"     : 0,
    "Date"          : "2016-03-09T02:20:09.022618116-08:00",
    "Size"          : 2543438,
    "SubPackages"   : null,
    "AutoDepends"   : null,
    "ManualDepends" : null,
    "BuildDepends"  : null,
    "Flags"         : [
                    "--with-jpeg8"
    ],
    "Patch"       : null,
    "Build"       : null,
    "Package"     : null,
    "PostInstall" : null,
    "Remove"      : null,
    "Files"       : [
                  "home/mrosset/.local/bin/cjpeg",
                  "home/mrosset/.local/bin/djpeg",
                  "home/mrosset/.local/bin/jpegtran",
                  "home/mrosset/.local/bin/rdjpgcom",
                  "home/mrosset/.local/bin/tjbench",
                  "home/mrosset/.local/bin/wrjpgcom",
                  "home/mrosset/.local/include/jconfig.h",
                  "home/mrosset/.local/include/jerror.h",
                  "home/mrosset/.local/include/jmorecfg.h",
                  "home/mrosset/.local/include/jpeglib.h",
                  "home/mrosset/.local/include/turbojpeg.h",
                  "home/mrosset/.local/lib/libjpeg.a",
                  "home/mrosset/.local/lib/libjpeg.la",
                  "home/mrosset/.local/lib/libjpeg.so",
                  "home/mrosset/.local/lib/libjpeg.so.8",
                  "home/mrosset/.local/lib/libjpeg.so.8.0.2",
                  "home/mrosset/.local/lib/libturbojpeg.a",
                  "home/mrosset/.local/lib/libturbojpeg.la",
                  "home/mrosset/.local/lib/libturbojpeg.so",
                  "home/mrosset/.local/lib/libturbojpeg.so.0",
                  "home/mrosset/.local/lib/libturbojpeg.so.0.1.0",
                  "home/mrosset/.local/share/doc/libjpeg-turbo/README",
                  "home/mrosset/.local/share/doc/libjpeg-turbo/README-turbo.txt",
                  "home/mrosset/.local/share/doc/libjpeg-turbo/example.c",
                  "home/mrosset/.local/share/doc/libjpeg-turbo/libjpeg.txt",
                  "home/mrosset/.local/share/doc/libjpeg-turbo/structure.txt",
                  "home/mrosset/.local/share/doc/libjpeg-turbo/usage.txt",
                  "home/mrosset/.local/share/doc/libjpeg-turbo/wizard.txt",
                  "home/mrosset/.local/share/man/man1/cjpeg.1",
                  "home/mrosset/.local/share/man/man1/djpeg.1",
                  "home/mrosset/.local/share/man/man1/jpegtran.1",
                  "home/mrosset/.local/share/man/man1/rdjpgcom.1",
                  "home/mrosset/.local/share/man/man1/wrjpgcom.1"
    ]
}
