{
    "Name"         : "ccache",
    "Version"      : "3.1.7",
    "Url"          : "http://samba.org/ftp/ccache/ccache-3.1.7.tar.gz",
    "Group"        : "core",
    "StageDir"     : "",
    "Inherit"      : "gnu-nostrip",
    "BuildInStage" : false,
    "Date"         : "2016-02-12T14:40:19.492831906-08:00",
    "Size"         : 97600,
    "SubPackages"  : null,
    "Depends"      : [
                   "glibc",
                   "zlib"
    ],             
    "Flags"        : null,
    "Patch"        : null,
    "Build"        : null,
    "Package"      : [
                   "mkdir -p $PKGDIR/$PREFIX/lib/ccache",
                   "ln -s $PREFIX/bin/ccache $PKGDIR/$PREFIX/lib/ccache/gcc",
                   "ln -s $PREFIX/bin/ccache $PKGDIR/$PREFIX/lib/ccache/clang",
                   "ln -s $PREFIX/bin/ccache $PKGDIR/$PREFIX/lib/ccache/g++",
                   "ln -s $PREFIX/bin/ccache $PKGDIR/$PREFIX/lib/ccache/cpp",
                   "ln -s $PREFIX/bin/ccache $PKGDIR/$PREFIX/lib/ccache/i686-via-linux-gnu-gcc"
    ],             
    "PostInstall"  : null,
    "Remove"       : null,
    "Files"        : [
                   "home/mrosset/install/bin/ccache",
                   "home/mrosset/install/lib/ccache/clang",
                   "home/mrosset/install/lib/ccache/cpp",
                   "home/mrosset/install/lib/ccache/g++",
                   "home/mrosset/install/lib/ccache/gcc",
                   "home/mrosset/install/lib/ccache/i686-via-linux-gnu-gcc"
    ]
}
