{
    "Name"         : "file",
    "Version"      : "5.32",
    "Url"          : "http://fossies.org/linux/misc/file-{{.Version}}.tar.gz",
    "Group"        : "core",
    "StageDir"     : "",
    "Inherit"      : "gnu",
    "Oid"          : "B24D3D9AEB27DAFF85F3400F5BC838CB54E802340D225448600023A8EEABDE5E",
    "BuildInStage" : false,
    "IsRebuilt"    : true,
    "BuildTime"    : 9494663451,
    "Date"         : "2017-09-12T21:29:17.910804055-07:00",
    "Size"         : 5128518,
    "SubPackages"  : null,
    "AutoDepends"  : [
                   "glibc",
                   "zlib"
    ],
    "ManualDepends" : null,
    "BuildDepends"  : null,
    "Flags"         : null,
    "Patch"         : null,
    "Build"         : null,
    "Package"       : null,
    "PostInstall"   : null,
    "Remove"        : null,
    "Files"         : [
                    "via/bin/file",
                    "via/include/magic.h",
                    "via/lib/libmagic.la",
                    "via/lib/libmagic.so",
                    "via/lib/libmagic.so.1",
                    "via/lib/libmagic.so.1.0.0",
                    "via/share/misc/magic.mgc"
    ]
}
