{
    "Name"         : "file",
    "Version"      : "5.32",
    "Url"          : "http://fossies.org/linux/misc/file-{{.Version}}.tar.gz",
    "Group"        : "core",
    "StageDir"     : "",
    "Inherit"      : "gnu",
    "Cid"          : "QmP8xyo5vbgX8YLippcE93fHN8sk35uz5Md1Q2m9HrDbih",
    "BuildInStage" : false,
    "IsRebuilt"    : true,
    "BuildTime"    : 9494663451,
    "Date"         : "2019-01-14T04:47:15.747068713Z",
    "Size"         : 5128718,
    "SubPackages"  : null,
    "AutoDepends"  : [
                   "glibc"
    ],
    "ManualDepends" : null,
    "BuildDepends"  : null,
    "Flags"         : null,
    "Patch"         : null,
    "Build"         : null,
    "Package"       : null,
    "PostInstall"   : null,
    "Remove"        : null,
    "Files"         : [
                    "opt/via/bin/file",
                    "opt/via/include/magic.h",
                    "opt/via/lib/libmagic.la",
                    "opt/via/lib/libmagic.so",
                    "opt/via/lib/libmagic.so.1",
                    "opt/via/lib/libmagic.so.1.0.0",
                    "opt/via/share/misc/magic.mgc"
    ]
}
