{
    "Name"         : "gawk",
    "Version"      : "4.1.3",
    "Url"          : "http://mirrors.kernel.org/gnu/gawk/gawk-4.1.3.tar.gz",
    "Group"        : "core",
    "StageDir"     : "",
    "Inherit"      : "gnu",
    "Cid"          : "QmTWZCVeZAaCEMLQvs8K2MEXG51QCaaxiVa7rMJ3LAyLK2",
    "BuildInStage" : false,
    "IsRebuilt"    : true,
    "BuildTime"    : 19356772859,
    "Date"         : "2019-01-13T21:04:44.625473963-08:00",
    "Size"         : 1437906,
    "SubPackages"  : null,
    "AutoDepends"  : [
                   "glibc",
                   "gmp",
                   "mpfr"
    ],
    "ManualDepends" : null,
    "BuildDepends"  : null,
    "Flags"         : null,
    "Patch"         : null,
    "Build"         : null,
    "Package"       : null,
    "PostInstall"   : null,
    "Remove"        : null,
    "Files"         : [
                    "opt/via/bin/awk",
                    "opt/via/bin/gawk",
                    "opt/via/bin/gawk-4.1.3",
                    "opt/via/bin/igawk",
                    "opt/via/include/gawkapi.h",
                    "opt/via/lib/awk/grcat",
                    "opt/via/lib/awk/pwcat",
                    "opt/via/lib/gawk/filefuncs.so",
                    "opt/via/lib/gawk/fnmatch.so",
                    "opt/via/lib/gawk/fork.so",
                    "opt/via/lib/gawk/inplace.so",
                    "opt/via/lib/gawk/ordchr.so",
                    "opt/via/lib/gawk/readdir.so",
                    "opt/via/lib/gawk/readfile.so",
                    "opt/via/lib/gawk/revoutput.so",
                    "opt/via/lib/gawk/revtwoway.so",
                    "opt/via/lib/gawk/rwarray.so",
                    "opt/via/lib/gawk/testext.so",
                    "opt/via/lib/gawk/time.so",
                    "opt/via/share/awk/assert.awk",
                    "opt/via/share/awk/bits2str.awk",
                    "opt/via/share/awk/cliff_rand.awk",
                    "opt/via/share/awk/ctime.awk",
                    "opt/via/share/awk/ftrans.awk",
                    "opt/via/share/awk/getopt.awk",
                    "opt/via/share/awk/gettime.awk",
                    "opt/via/share/awk/group.awk",
                    "opt/via/share/awk/inplace.awk",
                    "opt/via/share/awk/join.awk",
                    "opt/via/share/awk/libintl.awk",
                    "opt/via/share/awk/noassign.awk",
                    "opt/via/share/awk/ord.awk",
                    "opt/via/share/awk/passwd.awk",
                    "opt/via/share/awk/processarray.awk",
                    "opt/via/share/awk/quicksort.awk",
                    "opt/via/share/awk/readable.awk",
                    "opt/via/share/awk/readfile.awk",
                    "opt/via/share/awk/rewind.awk",
                    "opt/via/share/awk/round.awk",
                    "opt/via/share/awk/shellquote.awk",
                    "opt/via/share/awk/strtonum.awk",
                    "opt/via/share/awk/walkarray.awk",
                    "opt/via/share/awk/zerofile.awk"
    ]
}
